okadminfinder/__init__.py
okadminfinder/_utils.py
okadminfinder/app.py
okadminfinder/assets/admin-panel_links.yml
okadminfinder/assets/user-agents.yml
okadminfinder/cache.py
okadminfinder/credit.py
okadminfinder/errors_handler.py
okadminfinder/exceptions.py
okadminfinder/logging.py
okadminfinder/network.py
okadminfinder/process.py
okadminfinder/version.py
okadminfinder-2.0.0.dist-info/LICENSE
okadminfinder-2.0.0.dist-info/METADATA
okadminfinder-2.0.0.dist-info/WHEEL
okadminfinder-2.0.0.dist-info/entry_points.txt
okadminfinder-2.0.0.dist-info/RECORD
