Metadata-Version: 2.3
Name: okadminfinder
Version: 2.0.0
Summary: OKadminFinder: open-source tool designed to help administrators and penetration testers discover admin panels, directories, and subdomains of a website.
License: MIT
Keywords: admin panel,admin,panel,finder,directory,fuzz,subdomain,security,pentest,okadminfinder,web
Author: mIcHyAmRaNe
Author-email: 6m63er17c@mozmail.com
Maintainer: mIcHyAmRaNe
Maintainer-email: 6m63er17c@mozmail.com
Requires-Python: >=3.7
Classifier: Programming Language :: Python :: 3
Classifier: Programming Language :: Python :: 3.7
Classifier: Programming Language :: Python :: 3.8
Classifier: Programming Language :: Python :: 3.9
Classifier: Programming Language :: Python :: 3.10
Classifier: Programming Language :: Python :: 3.11
Classifier: Programming Language :: Python :: 3.12
Classifier: Programming Language :: Python :: 3.13
Classifier: License :: OSI Approved :: MIT License
Classifier: Operating System :: OS Independent
Provides-Extra: dev
Requires-Dist: diskcache (>=5.6.3)
Requires-Dist: pytest (>=8.3.4) ; extra == "dev"
Requires-Dist: pyyaml (>=6.0.2)
Requires-Dist: rich (>=13.9.4)
Requires-Dist: ruff (>=0.8.5) ; extra == "dev"
Requires-Dist: typer (>=0.15.1)
Requires-Dist: urllib3[socks] (>=2.3.0)
Project-URL: Bug Tracker, https://github.com/mIcHyAmRaNe/okadminfinder/issues
Project-URL: Homepage, https://github.com/mIcHyAmRaNe/okadminfinder
Project-URL: Repository, https://github.com/mIcHyAmRaNe/okadminfinder
